kytchen/.DS_Store
kytchen/__init__.py
kytchen/ingredient.py
kytchen/mealplan.py
kytchen/recipe.py
kytchen-1.0.0a1.dist-info/METADATA
kytchen-1.0.0a1.dist-info/WHEEL
kytchen-1.0.0a1.dist-info/licenses/LICENSE
kytchen-1.0.0a1.dist-info/RECORD
