Metadata-Version: 2.1
Name: kytchen
Version: 1.0.0a1
Summary: Handle your recipes and organise your meal plans
Project-URL: Homepage, https://sgc.ink/work/
Project-URL: Repository, https://github.com/gonzalezcastillo/kytchen
Author: Samuel González-Castillo
License: MIT License
License-File: LICENSE
Keywords: cooking,recipes
Classifier: Development Status :: 3 - Alpha
Classifier: License :: OSI Approved :: MIT License
Classifier: Operating System :: OS Independent
Classifier: Programming Language :: Python :: 3
Classifier: Topic :: Utilities
Requires-Python: >=3.9
